maxwent/__init__.py
maxwent/example_utils.py
maxwent/tch/__init__.py
maxwent/tch/layers.py
maxwent/tch/model.py
maxwent/tch/utils.py
maxwent/tf/__init__.py
maxwent/tf/example_utils.py
maxwent/tf/layers.py
maxwent/tf/model.py
maxwent/tf/utils.py
maxwent-0.3.0.dist-info/LICENSE
maxwent-0.3.0.dist-info/METADATA
maxwent-0.3.0.dist-info/WHEEL
maxwent-0.3.0.dist-info/top_level.txt
maxwent-0.3.0.dist-info/RECORD
