Metadata-Version: 2.2
Name: maxwent
Version: 0.3.0
Summary: Maximum Weight Entropy
Author: Antoine de Mathelin
Author-email: antoine.demat@gmail.com
License-File: LICENSE
Provides-Extra: tf
Requires-Dist: tensorflow>=2.16; extra == "tf"
Provides-Extra: torch
Requires-Dist: torch>=1.0; extra == "torch"
Dynamic: author
Dynamic: author-email
Dynamic: description
Dynamic: description-content-type
Dynamic: provides-extra
Dynamic: summary
